multi_ai_hub.py
multiaihub-0.1.7.dist-info/LICENSE
multiaihub-0.1.7.dist-info/METADATA
multiaihub-0.1.7.dist-info/WHEEL
multiaihub-0.1.7.dist-info/top_level.txt
multiaihub-0.1.7.dist-info/RECORD
