Metadata-Version: 2.1
Name: multiaihub
Version: 0.1.7
Summary: MAH makes it easy to send the same prompt to multiple LLMs
Author: Mike Wolfson
Author-email: mike@ableandroid.com
License: Apache License 2.0
License-File: LICENSE
Requires-Dist: python-dotenv ==1.0.0
Requires-Dist: google.generativeai ==0.5.4
Requires-Dist: openai ==1.35.2
Requires-Dist: anthropic ==0.17.0
